jupyterlab_lego_boost/__init__.py
jupyterlab_lego_boost/_version.py
jupyterlab_lego_boost-0.1.0a4.data/data/share/jupyter/labextensions/jupyterlab-lego-boost/package.json
jupyterlab_lego_boost-0.1.0a4.data/data/share/jupyter/labextensions/jupyterlab-lego-boost/static/156.6ce06a10f5208e8fea83.js
jupyterlab_lego_boost-0.1.0a4.data/data/share/jupyter/labextensions/jupyterlab-lego-boost/static/156.6ce06a10f5208e8fea83.js.map
jupyterlab_lego_boost-0.1.0a4.data/data/share/jupyter/labextensions/jupyterlab-lego-boost/static/194.c420a6d59b90073e88af.js
jupyterlab_lego_boost-0.1.0a4.data/data/share/jupyter/labextensions/jupyterlab-lego-boost/static/194.c420a6d59b90073e88af.js.map
jupyterlab_lego_boost-0.1.0a4.data/data/share/jupyter/labextensions/jupyterlab-lego-boost/static/222.620a610db8fb1e06aad7.js
jupyterlab_lego_boost-0.1.0a4.data/data/share/jupyter/labextensions/jupyterlab-lego-boost/static/222.620a610db8fb1e06aad7.js.map
jupyterlab_lego_boost-0.1.0a4.data/data/share/jupyter/labextensions/jupyterlab-lego-boost/static/250.6db6d7189e5fd61fc2be.js
jupyterlab_lego_boost-0.1.0a4.data/data/share/jupyter/labextensions/jupyterlab-lego-boost/static/250.6db6d7189e5fd61fc2be.js.map
jupyterlab_lego_boost-0.1.0a4.data/data/share/jupyter/labextensions/jupyterlab-lego-boost/static/287.fbaee6b503bba9814192.js
jupyterlab_lego_boost-0.1.0a4.data/data/share/jupyter/labextensions/jupyterlab-lego-boost/static/287.fbaee6b503bba9814192.js.map
jupyterlab_lego_boost-0.1.0a4.data/data/share/jupyter/labextensions/jupyterlab-lego-boost/static/310.ebe278c22b17c846b81e.js
jupyterlab_lego_boost-0.1.0a4.data/data/share/jupyter/labextensions/jupyterlab-lego-boost/static/310.ebe278c22b17c846b81e.js.map
jupyterlab_lego_boost-0.1.0a4.data/data/share/jupyter/labextensions/jupyterlab-lego-boost/static/318.107d13a3260af3968c03.js
jupyterlab_lego_boost-0.1.0a4.data/data/share/jupyter/labextensions/jupyterlab-lego-boost/static/318.107d13a3260af3968c03.js.map
jupyterlab_lego_boost-0.1.0a4.dist-info/METADATA
jupyterlab_lego_boost-0.1.0a4.dist-info/WHEEL
jupyterlab_lego_boost-0.1.0a4.dist-info/licenses/LICENSE
jupyterlab_lego_boost-0.1.0a4.dist-info/RECORD
