Metadata-Version: 2.3
Name: jupyterlab_lego_boost
Version: 0.1.0a4
Dynamic: Keywords
Summary: Blockly extension for JupyterLab to control the Lego Boost
Project-URL: Homepage, https://github.com/jupyter-robotics/jupyterlab-lego-boost
Project-URL: Bug Tracker, https://github.com/jupyter-robotics/jupyterlab-lego-boost/issues
Project-URL: Repository, https://github.com/jupyter-robotics/jupyterlab-lego-boost.git
Author-email: Denisa Checiu <denisa.checiu@quantstack.net>
License: BSD 3-Clause License
License-File: LICENSE
Classifier: Framework :: Jupyter
Classifier: Framework :: Jupyter :: JupyterLab
Classifier: Framework :: Jupyter :: JupyterLab :: 4
Classifier: Framework :: Jupyter :: JupyterLab :: Extensions
Classifier: Framework :: Jupyter :: JupyterLab :: Extensions :: Prebuilt
Classifier: License :: OSI Approved :: BSD License
Classifier: Programming Language :: Python
Classifier: Programming Language :: Python :: 3
Classifier: Programming Language :: Python :: 3.8
Classifier: Programming Language :: Python :: 3.9
Classifier: Programming Language :: Python :: 3.10
Classifier: Programming Language :: Python :: 3.11
Classifier: Programming Language :: Python :: 3.12
Requires-Python: >=3.8
Requires-Dist: bleak<1,>=0.22.2
Requires-Dist: jupyterlab-blockly<0.4,>=0.3.3
Requires-Dist: pylgbst<2,>=1.3.0
Provides-Extra: dev
Requires-Dist: click; extra == 'dev'
Requires-Dist: jupyter-releaser; extra == 'dev'
Provides-Extra: env
Requires-Dist: bleak; extra == 'env'
Requires-Dist: pylgbst; extra == 'env'
